[{"t":"39","i":"39","s":"241615256183052","n":"Rizki Ramdan Hidayat","u":null,"p":"https:\/\/graph.facebook.com\/241615256183052\/picture?type=large","l":null,"f":null},{"t":"37","i":"37","s":"143427769470200","n":"Widia Ani Ani","u":null,"p":"https:\/\/graph.facebook.com\/143427769470200\/picture?type=large","l":null,"f":null},{"t":"18","i":"18","s":"10205183045449641","n":"Ahmad Sofyan","u":null,"p":"https:\/\/graph.facebook.com\/10205183045449641\/picture?type=large","l":null,"f":null},{"t":"16","i":"16","s":"426012614414799","n":"TonNo Saputra","u":null,"p":"https:\/\/graph.facebook.com\/426012614414799\/picture?type=large","l":null,"f":null},{"t":"8","i":"8","s":"359471067725631","n":"Sebastyan Johan","u":null,"p":"https:\/\/graph.facebook.com\/359471067725631\/picture?type=large","l":null,"f":null},{"t":"6","i":"6","s":"1282990111727761","n":"Sandhy Ashkenazi Yudha","u":null,"p":"https:\/\/graph.facebook.com\/1282990111727761\/picture?type=large","l":null,"f":null},{"t":"5","i":"5","s":"323350451377363","n":"Wulan","u":null,"p":"https:\/\/graph.facebook.com\/323350451377363\/picture?type=large","l":null,"f":null},{"t":"4","i":"4","s":"1085092241625173","n":"Jhepry Tkm","u":null,"p":"https:\/\/graph.facebook.com\/1085092241625173\/picture?type=large","l":null,"f":null},{"t":"4","i":"4","s":"233351130438842","n":"Barit Iku","u":null,"p":"https:\/\/graph.facebook.com\/233351130438842\/picture?type=large","l":null,"f":null},{"t":"3","i":"3","s":"1204145916373636","n":"Dayat Roman Syahputra","u":null,"p":"https:\/\/graph.facebook.com\/1204145916373636\/picture?type=large","l":null,"f":null}]