[{"t":"2","s":"1716013922021175","n":"Gerry Salim","u":null,"p":"https:\/\/graph.facebook.com\/1716013922021175\/picture?type=large","l":null,"f":null},{"t":"1","s":"462164467223143","n":"ANJANY RACING SPEED SHOP","u":null,"p":"https:\/\/graph.facebook.com\/462164467223143\/picture?type=large","l":null,"f":null},{"t":"1","s":"10201537984009607","n":"Al Abud Pramono","u":null,"p":"https:\/\/graph.facebook.com\/10201537984009607\/picture?type=large","l":null,"f":null},{"t":"1","s":"1645044675524400","n":"Agung Setiawan","u":null,"p":"https:\/\/graph.facebook.com\/1645044675524400\/picture?type=large","l":null,"f":null},{"t":"1","s":"10209807786645086","n":"Budiman Isfebrianto","u":null,"p":"https:\/\/graph.facebook.com\/10209807786645086\/picture?type=large","l":null,"f":null}]